manuscript_cover_letter/__init__.py
manuscript_cover_letter/about.py
manuscript_cover_letter/desktop.py
manuscript_cover_letter/program.py
manuscript_cover_letter/wabout.py
manuscript_cover_letter/icons/logo.png
manuscript_cover_letter/modules/__init__.py
manuscript_cover_letter/modules/lib_cover_basic.py
manuscript_cover_letter/modules/lib_cover_style1.py
manuscript_cover_letter-0.1.5.dist-info/licenses/LICENSE
manuscript_cover_letter-0.1.5.dist-info/METADATA
manuscript_cover_letter-0.1.5.dist-info/WHEEL
manuscript_cover_letter-0.1.5.dist-info/entry_points.txt
manuscript_cover_letter-0.1.5.dist-info/top_level.txt
manuscript_cover_letter-0.1.5.dist-info/RECORD
